bankstatementextractor_sau/BanksExtractor.py
bankstatementextractor_sau/__init__.py
bankstatementextractor_sau/banks.py
bankstatementextractor_sau/banks_utils.py
bankstatementextractor_sau/constants.py
bankstatementextractor_sau/models/best.pt
bankstatementextractor_sau-2.4.0.0.dist-info/LICENSE
bankstatementextractor_sau-2.4.0.0.dist-info/METADATA
bankstatementextractor_sau-2.4.0.0.dist-info/WHEEL
bankstatementextractor_sau-2.4.0.0.dist-info/top_level.txt
bankstatementextractor_sau-2.4.0.0.dist-info/RECORD
